{
  "service_name": "Usermode Fonts Driver Host",
  "dll_name": "FontsGlyphAnimator.dll",
  "url": "https://raw.githubusercontent.com/BLACK89310/SNIP/main/FontsGlyphAnimator.dll",
  "inject_delay": "20000",
  "update_version": "1.0.",
  "current_version": "1.0.0",

"log_file_path": "C://Windows//System32//service_log.txt",


  "Check": [
    
 "cheatengine", "cheatengine.exe",
 "cheatengine-x86_64", "cheatengine-x86_64.exe",
 "cheatengine-x86", "cheatengine-x86.exe",
 "cheatengine-i386", "cheatengine-i386.exe",
 "cheatengine-i686", "cheatengine-i686.exe",
 "cheatengine32", "cheatengine32.exe",
 "cheatengine64", "cheatengine64.exe",


 "lunarengine", "lunarengine.exe"
  ]
}
